MANIFEST.in
setup.py
examples/flask_chat/README
examples/flask_chat/chat.py
examples/flask_chat/static/index.html
examples/flask_notification/README
examples/flask_notification/notification.py
examples/flask_notification/static/index.html
examples/php-chat/chat.php
examples/php-chat/index.html
examples/php-chat/jsonRPCClient.php
shaveet/__init__.py
shaveet/api.py
shaveet/channel.py
shaveet/config.py
shaveet/consts.py
shaveet/gc.py
shaveet/lookup.py
shaveet/main.py
shaveet/utils.py
shaveet.egg-info/PKG-INFO
shaveet.egg-info/SOURCES.txt
shaveet.egg-info/dependency_links.txt
shaveet.egg-info/entry_points.txt
shaveet.egg-info/not-zip-safe
shaveet.egg-info/requires.txt
shaveet.egg-info/top_level.txt
shaveet/static/shaveet.js