Metadata-Version: 1.0
Name: shaveet
Version: 0.1.6
Summary: Shaveet comet server
Home-page: https://github.com/urielka/shaveet
Author: Uriel Katz
Author-email: uriel.katz@gmail.com
License: MIT
Download-URL: https://github.com/urielka/shaveet/downloads
Keywords: comet gevent server
Platform: UNKNOWN
